binalyzer_core/__init__.py
binalyzer_core/binalyzer.py
binalyzer_core/binding.py
binalyzer_core/data_provider.py
binalyzer_core/extension.py
binalyzer_core/factory.py
binalyzer_core/modify.py
binalyzer_core/properties.py
binalyzer_core/template.py
binalyzer_core/template_engine.py
binalyzer_core/template_provider.py
binalyzer_core/utils.py
binalyzer_core/value_provider.py
binalyzer_core-1.0.5.data/data/CHANGELOG.md
binalyzer_core-1.0.5.dist-info/AUTHORS
binalyzer_core-1.0.5.dist-info/LICENSE.rst
binalyzer_core-1.0.5.dist-info/METADATA
binalyzer_core-1.0.5.dist-info/WHEEL
binalyzer_core-1.0.5.dist-info/top_level.txt
binalyzer_core-1.0.5.dist-info/RECORD
